<?xml version="1.0" ?>
<FlowMonitor>
  <FlowStats>
    <Flow flowId="1" timeFirstTxPacket="+1.09613e+08ns" timeFirstRxPacket="+1.10446e+08ns" timeLastTxPacket="+2.61973e+09ns" timeLastRxPacket="+2.62045e+09ns" delaySum="+2.99378e+09ns" jitterSum="+2.45091e+08ns" lastDelay="+717440ns" txBytes="428808" rxBytes="428808" txPackets="4204" rxPackets="4204" lostPackets="0" timesForwarded="0">
      <delayHistogram nBins="34" >
        <bin index="0" start="0" width="0.001" count="3807" />
        <bin index="1" start="0.001" width="0.001" count="189" />
        <bin index="2" start="0.002" width="0.001" count="133" />
        <bin index="3" start="0.003" width="0.001" count="37" />
        <bin index="4" start="0.004" width="0.001" count="2" />
        <bin index="5" start="0.005" width="0.001" count="1" />
        <bin index="6" start="0.006" width="0.001" count="1" />
        <bin index="7" start="0.007" width="0.001" count="1" />
        <bin index="8" start="0.008" width="0.001" count="2" />
        <bin index="9" start="0.009" width="0.001" count="1" />
        <bin index="10" start="0.01" width="0.001" count="1" />
        <bin index="11" start="0.011" width="0.001" count="1" />
        <bin index="12" start="0.012" width="0.001" count="2" />
        <bin index="13" start="0.013" width="0.001" count="1" />
        <bin index="14" start="0.014" width="0.001" count="1" />
        <bin index="15" start="0.015" width="0.001" count="1" />
        <bin index="16" start="0.016" width="0.001" count="1" />
        <bin index="17" start="0.017" width="0.001" count="2" />
        <bin index="18" start="0.018" width="0.001" count="1" />
        <bin index="19" start="0.019" width="0.001" count="1" />
        <bin index="20" start="0.02" width="0.001" count="1" />
        <bin index="21" start="0.021" width="0.001" count="2" />
        <bin index="22" start="0.022" width="0.001" count="1" />
        <bin index="23" start="0.023" width="0.001" count="1" />
        <bin index="24" start="0.024" width="0.001" count="1" />
        <bin index="25" start="0.025" width="0.001" count="2" />
        <bin index="26" start="0.026" width="0.001" count="1" />
        <bin index="27" start="0.027" width="0.001" count="1" />
        <bin index="28" start="0.028" width="0.001" count="1" />
        <bin index="29" start="0.029" width="0.001" count="2" />
        <bin index="30" start="0.03" width="0.001" count="1" />
        <bin index="31" start="0.031" width="0.001" count="1" />
        <bin index="32" start="0.032" width="0.001" count="1" />
        <bin index="33" start="0.033" width="0.001" count="2" />
      </delayHistogram>
      <jitterHistogram nBins="34" >
        <bin index="0" start="0" width="0.001" count="4202" />
        <bin index="33" start="0.033" width="0.001" count="1" />
      </jitterHistogram>
      <packetSizeHistogram nBins="6" >
        <bin index="5" start="100" width="20" count="4204" />
      </packetSizeHistogram>
      <flowInterruptionsHistogram nBins="5" >
        <bin index="0" start="0" width="0.25" count="4" />
        <bin index="1" start="0.25" width="0.25" count="1" />
        <bin index="2" start="0.5" width="0.25" count="1" />
        <bin index="4" start="1" width="0.25" count="1" />
      </flowInterruptionsHistogram>
    </Flow>
    <Flow flowId="2" timeFirstTxPacket="+5.53763e+08ns" timeFirstRxPacket="+5.6342e+08ns" timeLastTxPacket="+1.88122e+09ns" timeLastRxPacket="+1.89088e+09ns" delaySum="+4.8285e+07ns" jitterSum="+0ns" lastDelay="+9.657e+06ns" txBytes="6025" rxBytes="6025" txPackets="5" rxPackets="5" lostPackets="0" timesForwarded="0">
      <delayHistogram nBins="10" >
        <bin index="9" start="0.009" width="0.001" count="5" />
      </delayHistogram>
      <jitterHistogram nBins="1" >
        <bin index="0" start="0" width="0.001" count="4" />
      </jitterHistogram>
      <packetSizeHistogram nBins="61" >
        <bin index="60" start="1200" width="20" count="5" />
      </packetSizeHistogram>
      <flowInterruptionsHistogram nBins="4" >
        <bin index="0" start="0" width="0.25" count="3" />
        <bin index="3" start="0.75" width="0.25" count="1" />
      </flowInterruptionsHistogram>
    </Flow>
    <Flow flowId="3" timeFirstTxPacket="+5.90869e+08ns" timeFirstRxPacket="+6.00526e+08ns" timeLastTxPacket="+2.74784e+09ns" timeLastRxPacket="+2.75749e+09ns" delaySum="+4.8285e+07ns" jitterSum="+0ns" lastDelay="+9.657e+06ns" txBytes="6025" rxBytes="6025" txPackets="5" rxPackets="5" lostPackets="0" timesForwarded="0">
      <delayHistogram nBins="10" >
        <bin index="9" start="0.009" width="0.001" count="5" />
      </delayHistogram>
      <jitterHistogram nBins="1" >
        <bin index="0" start="0" width="0.001" count="4" />
      </jitterHistogram>
      <packetSizeHistogram nBins="61" >
        <bin index="60" start="1200" width="20" count="5" />
      </packetSizeHistogram>
      <flowInterruptionsHistogram nBins="3" >
        <bin index="1" start="0.25" width="0.25" count="2" />
        <bin index="2" start="0.5" width="0.25" count="2" />
      </flowInterruptionsHistogram>
    </Flow>
    <Flow flowId="4" timeFirstTxPacket="+6.03547e+08ns" timeFirstRxPacket="+6.04196e+08ns" timeLastTxPacket="+2.7298e+09ns" timeLastRxPacket="+2.72987e+09ns" delaySum="+6.66267e+08ns" jitterSum="+4.10562e+07ns" lastDelay="+61100ns" txBytes="149468" rxBytes="149468" txPackets="1892" rxPackets="1892" lostPackets="0" timesForwarded="0">
      <delayHistogram nBins="2" >
        <bin index="0" start="0" width="0.001" count="1842" />
        <bin index="1" start="0.001" width="0.001" count="50" />
      </delayHistogram>
      <jitterHistogram nBins="1" >
        <bin index="0" start="0" width="0.001" count="1891" />
      </jitterHistogram>
      <packetSizeHistogram nBins="4" >
        <bin index="3" start="60" width="20" count="1892" />
      </packetSizeHistogram>
      <flowInterruptionsHistogram nBins="4" >
        <bin index="1" start="0.25" width="0.25" count="1" />
        <bin index="2" start="0.5" width="0.25" count="1" />
        <bin index="3" start="0.75" width="0.25" count="1" />
      </flowInterruptionsHistogram>
    </Flow>
    <Flow flowId="5" timeFirstTxPacket="+6.65865e+08ns" timeFirstRxPacket="+6.66514e+08ns" timeLastTxPacket="+2.0152e+09ns" timeLastRxPacket="+2.01575e+09ns" delaySum="+5.01835e+09ns" jitterSum="+1.2547e+08ns" lastDelay="+545776ns" txBytes="1244250" rxBytes="1244250" txPackets="15750" rxPackets="15750" lostPackets="0" timesForwarded="0">
      <delayHistogram nBins="2" >
        <bin index="0" start="0" width="0.001" count="15612" />
        <bin index="1" start="0.001" width="0.001" count="138" />
      </delayHistogram>
      <jitterHistogram nBins="1" >
        <bin index="0" start="0" width="0.001" count="15749" />
      </jitterHistogram>
      <packetSizeHistogram nBins="4" >
        <bin index="3" start="60" width="20" count="15750" />
      </packetSizeHistogram>
      <flowInterruptionsHistogram nBins="3" >
        <bin index="0" start="0" width="0.25" count="2" />
        <bin index="1" start="0.25" width="0.25" count="2" />
        <bin index="2" start="0.5" width="0.25" count="1" />
      </flowInterruptionsHistogram>
    </Flow>
    <Flow flowId="6" timeFirstTxPacket="+8.49143e+08ns" timeFirstRxPacket="+8.49792e+08ns" timeLastTxPacket="+2.74898e+09ns" timeLastRxPacket="+2.74926e+09ns" delaySum="+1.55244e+09ns" jitterSum="+8.62265e+07ns" lastDelay="+278490ns" txBytes="340174" rxBytes="340174" txPackets="4306" rxPackets="4306" lostPackets="0" timesForwarded="0">
      <delayHistogram nBins="3" >
        <bin index="0" start="0" width="0.001" count="4184" />
        <bin index="1" start="0.001" width="0.001" count="68" />
        <bin index="2" start="0.002" width="0.001" count="54" />
      </delayHistogram>
      <jitterHistogram nBins="1" >
        <bin index="0" start="0" width="0.001" count="4305" />
      </jitterHistogram>
      <packetSizeHistogram nBins="4" >
        <bin index="3" start="60" width="20" count="4306" />
      </packetSizeHistogram>
      <flowInterruptionsHistogram nBins="3" >
        <bin index="0" start="0" width="0.25" count="3" />
        <bin index="1" start="0.25" width="0.25" count="2" />
        <bin index="2" start="0.5" width="0.25" count="1" />
      </flowInterruptionsHistogram>
    </Flow>
    <Flow flowId="7" timeFirstTxPacket="+1.51459e+09ns" timeFirstRxPacket="+1.51459e+09ns" timeLastTxPacket="+2.9527e+09ns" timeLastRxPacket="+2.9527e+09ns" delaySum="+1.71704e+06ns" jitterSum="+0ns" lastDelay="+1013ns" txBytes="286455" rxBytes="286455" txPackets="1695" rxPackets="1695" lostPackets="0" timesForwarded="0">
      <delayHistogram nBins="1" >
        <bin index="0" start="0" width="0.001" count="1695" />
      </delayHistogram>
      <jitterHistogram nBins="1" >
        <bin index="0" start="0" width="0.001" count="1694" />
      </jitterHistogram>
      <packetSizeHistogram nBins="9" >
        <bin index="8" start="160" width="20" count="1695" />
      </packetSizeHistogram>
      <flowInterruptionsHistogram nBins="4" >
        <bin index="0" start="0" width="0.25" count="2" />
        <bin index="1" start="0.25" width="0.25" count="1" />
        <bin index="3" start="0.75" width="0.25" count="1" />
      </flowInterruptionsHistogram>
    </Flow>
  </FlowStats>
  <Ipv4FlowClassifier>
    <Flow flowId="7" sourceAddress="10.0.1.1" destinationAddress="10.0.1.2" protocol="17" sourcePort="49153" destinationPort="9">
      <Dscp value="0x0" packets="1695" />
    </Flow>
    <Flow flowId="1" sourceAddress="10.0.3.1" destinationAddress="10.0.3.2" protocol="17" sourcePort="49154" destinationPort="9">
      <Dscp value="0x0" packets="4204" />
    </Flow>
    <Flow flowId="2" sourceAddress="10.0.4.1" destinationAddress="10.0.4.2" protocol="17" sourcePort="49155" destinationPort="9">
      <Dscp value="0x0" packets="5" />
    </Flow>
    <Flow flowId="5" sourceAddress="10.0.5.1" destinationAddress="10.0.5.2" protocol="17" sourcePort="49156" destinationPort="9">
      <Dscp value="0x0" packets="15750" />
    </Flow>
    <Flow flowId="3" sourceAddress="10.1.2.1" destinationAddress="10.1.2.2" protocol="17" sourcePort="49153" destinationPort="9">
      <Dscp value="0x0" packets="5" />
    </Flow>
    <Flow flowId="6" sourceAddress="10.1.4.1" destinationAddress="10.1.4.2" protocol="17" sourcePort="49154" destinationPort="9">
      <Dscp value="0x0" packets="4306" />
    </Flow>
    <Flow flowId="4" sourceAddress="10.2.3.1" destinationAddress="10.2.3.2" protocol="17" sourcePort="49153" destinationPort="9">
      <Dscp value="0x0" packets="1892" />
    </Flow>
  </Ipv4FlowClassifier>
  <Ipv6FlowClassifier>
  </Ipv6FlowClassifier>
  <FlowProbes>
    <FlowProbe index="0">
      <FlowStats  flowId="1" packets="4204" bytes="428808" delayFromFirstProbeSum="+0ns" >
      </FlowStats>
      <FlowStats  flowId="2" packets="5" bytes="6025" delayFromFirstProbeSum="+0ns" >
      </FlowStats>
      <FlowStats  flowId="5" packets="15750" bytes="1244250" delayFromFirstProbeSum="+0ns" >
      </FlowStats>
      <FlowStats  flowId="7" packets="1695" bytes="286455" delayFromFirstProbeSum="+0ns" >
      </FlowStats>
    </FlowProbe>
    <FlowProbe index="1">
    </FlowProbe>
    <FlowProbe index="2">
      <FlowStats  flowId="3" packets="5" bytes="6025" delayFromFirstProbeSum="+0ns" >
      </FlowStats>
      <FlowStats  flowId="6" packets="4306" bytes="340174" delayFromFirstProbeSum="+0ns" >
      </FlowStats>
      <FlowStats  flowId="7" packets="1695" bytes="286455" delayFromFirstProbeSum="+1.71704e+06ns" >
      </FlowStats>
    </FlowProbe>
    <FlowProbe index="3">
    </FlowProbe>
    <FlowProbe index="4">
      <FlowStats  flowId="3" packets="5" bytes="6025" delayFromFirstProbeSum="+4.8285e+07ns" >
      </FlowStats>
      <FlowStats  flowId="4" packets="1892" bytes="149468" delayFromFirstProbeSum="+0ns" >
      </FlowStats>
    </FlowProbe>
    <FlowProbe index="5">
    </FlowProbe>
    <FlowProbe index="6">
      <FlowStats  flowId="1" packets="4204" bytes="428808" delayFromFirstProbeSum="+2.99378e+09ns" >
      </FlowStats>
      <FlowStats  flowId="4" packets="1892" bytes="149468" delayFromFirstProbeSum="+6.66267e+08ns" >
      </FlowStats>
    </FlowProbe>
    <FlowProbe index="7">
    </FlowProbe>
    <FlowProbe index="8">
      <FlowStats  flowId="2" packets="5" bytes="6025" delayFromFirstProbeSum="+4.8285e+07ns" >
      </FlowStats>
      <FlowStats  flowId="6" packets="4306" bytes="340174" delayFromFirstProbeSum="+1.55244e+09ns" >
      </FlowStats>
    </FlowProbe>
    <FlowProbe index="9">
    </FlowProbe>
    <FlowProbe index="10">
      <FlowStats  flowId="5" packets="15750" bytes="1244250" delayFromFirstProbeSum="+5.01835e+09ns" >
      </FlowStats>
    </FlowProbe>
    <FlowProbe index="11">
    </FlowProbe>
  </FlowProbes>
</FlowMonitor>
